rapid_latex_ocr/__init__.py
rapid_latex_ocr/config.yaml
rapid_latex_ocr/main.py
rapid_latex_ocr/models.py
rapid_latex_ocr/utils.py
rapid_latex_ocr/utils_load.py
rapid_latex_ocr-0.0.9.dist-info/LICENSE
rapid_latex_ocr-0.0.9.dist-info/METADATA
rapid_latex_ocr-0.0.9.dist-info/WHEEL
rapid_latex_ocr-0.0.9.dist-info/entry_points.txt
rapid_latex_ocr-0.0.9.dist-info/top_level.txt
rapid_latex_ocr-0.0.9.dist-info/RECORD
